devopstool/__init__.py
devopstool/cli.py
devopstool/dockerhub_list_tags.py
devopstoolscli-1.0.dist-info/METADATA
devopstoolscli-1.0.dist-info/WHEEL
devopstoolscli-1.0.dist-info/entry_points.txt
devopstoolscli-1.0.dist-info/top_level.txt
devopstoolscli-1.0.dist-info/RECORD
